qakeapi/__init__.py
qakeapi/py.typed
qakeapi/core/__init__.py
qakeapi/core/app.py
qakeapi/core/auth.py
qakeapi/core/background.py
qakeapi/core/caching.py
qakeapi/core/dependencies.py
qakeapi/core/exceptions.py
qakeapi/core/files.py
qakeapi/core/hybrid.py
qakeapi/core/logging.py
qakeapi/core/middleware.py
qakeapi/core/openapi.py
qakeapi/core/parallel.py
qakeapi/core/pipeline.py
qakeapi/core/rate_limit.py
qakeapi/core/reactive.py
qakeapi/core/request.py
qakeapi/core/response.py
qakeapi/core/router.py
qakeapi/core/validation.py
qakeapi/core/websocket.py
qakeapi-1.3.1.dist-info/licenses/LICENSE
qakeapi-1.3.1.dist-info/METADATA
qakeapi-1.3.1.dist-info/WHEEL
qakeapi-1.3.1.dist-info/top_level.txt
qakeapi-1.3.1.dist-info/RECORD
